jinja_tree/__init__.py
jinja_tree/app/__init__.py
jinja_tree/app/action.py
jinja_tree/app/config.py
jinja_tree/app/context.py
jinja_tree/app/jinja.py
jinja_tree/app/jinja_tree.py
jinja_tree/app/embedded_extensions/__init__.py
jinja_tree/app/embedded_extensions/double_quotes.py
jinja_tree/app/embedded_extensions/fnmatch.py
jinja_tree/app/embedded_extensions/from_json.py
jinja_tree/app/embedded_extensions/from_toml.py
jinja_tree/app/embedded_extensions/shell.py
jinja_tree/app/embedded_extensions/urlencode.py
jinja_tree/infra/__init__.py
jinja_tree/infra/utils.py
jinja_tree/infra/adapters/__init__.py
jinja_tree/infra/adapters/action.py
jinja_tree/infra/adapters/context.py
jinja_tree/infra/controllers/__init__.py
jinja_tree/infra/controllers/cli_common.py
jinja_tree/infra/controllers/cli_stdin.py
jinja_tree/infra/controllers/cli_tree.py
jinja_tree-0.7.4.dist-info/METADATA
jinja_tree-0.7.4.dist-info/WHEEL
jinja_tree-0.7.4.dist-info/entry_points.txt
jinja_tree-0.7.4.dist-info/licenses/LICENSE
jinja_tree-0.7.4.dist-info/RECORD
