Metadata-Version: 2.4
Name: jinja-tree
Version: 0.7.4
Summary: CLI to process jinja (jinja2) templates in a directory tree
Project-URL: Homepage, https://github.com/fabien-marty/jinja-tree
Project-URL: Repository, https://github.com/fabien-marty/jinja-tree
Author-email: Fabien MARTY <fabien.marty@botify.com>
License-Expression: MIT
License-File: LICENSE
Keywords: cli,jinja,jinja2,tree
Classifier: Development Status :: 4 - Beta
Classifier: Environment :: Console
Classifier: Intended Audience :: Developers
Classifier: License :: OSI Approved :: MIT License
Classifier: Programming Language :: Python :: 3
Classifier: Topic :: Software Development
Classifier: Topic :: Text Processing :: General
Classifier: Topic :: Utilities
Requires-Python: ~=3.8
Requires-Dist: dataclasses-json>=0.6.4
Requires-Dist: jinja2<4,>=3.1.2
Requires-Dist: python-dotenv>=1.0.0
Requires-Dist: rich>=13.7.0
Requires-Dist: stlog>=0.1.0
Requires-Dist: tomli<3,>=2.0.1
Requires-Dist: typer>=0.9.0
